[
  {"i":"0",  "hoten":"Vu Giang Nam",           "quancu":"q 10",        "phuongmoi":"Vuon Lai"},
  {"i":"1",  "hoten":"Le Hoang Long",          "quancu":"12",          "phuongmoi":"Thoi An"},
  {"i":"2",  "hoten":"Nguyen Le Thien An",     "quancu":"My Tho",      "phuongmoi":"My Tho"},
  {"i":"3",  "hoten":"Nguyen Duc Nghia",       "quancu":"Go Vao",      "phuongmoi":"Go Vap"},
  {"i":"4",  "hoten":"Nguyen Phong Phu",       "quancu":"7",           "phuongmoi":"Tan My"},
  {"i":"5",  "hoten":"Doan Son Tung",          "quancu":"12",          "phuongmoi":"Ha Huy Giap"},
  {"i":"6",  "hoten":"Tran Thanh Hieu Nguyen", "quancu":"Chau Thanh",  "phuongmoi":"Tay Ninh"}
]
